ircchallenge/__init__.py
ircchallenge/py.typed
ircchallenge-0.1.2.dist-info/LICENSE
ircchallenge-0.1.2.dist-info/METADATA
ircchallenge-0.1.2.dist-info/WHEEL
ircchallenge-0.1.2.dist-info/top_level.txt
ircchallenge-0.1.2.dist-info/RECORD
